{
  "id": "2510256",
  "name": "myblog",
  "font_family": "iconfont",
  "css_prefix_text": "icon",
  "description": "",
  "glyphs": [
    {
      "icon_id": "1400856",
      "name": "上一页",
      "font_class": "shangyiye",
      "unicode": "e617",
      "unicode_decimal": 58903
    },
    {
      "icon_id": "8530850",
      "name": "下拉",
      "font_class": "Group",
      "unicode": "e61b",
      "unicode_decimal": 58907
    },
    {
      "icon_id": "9697604",
      "name": "管理",
      "font_class": "icon_xinyong_xianxing_jijin-",
      "unicode": "e636",
      "unicode_decimal": 58934
    },
    {
      "icon_id": "579286",
      "name": "点赞",
      "font_class": "dianzan",
      "unicode": "e60c",
      "unicode_decimal": 58892
    },
    {
      "icon_id": "1314429",
      "name": "眼睛",
      "font_class": "yanjing",
      "unicode": "e60d",
      "unicode_decimal": 58893
    },
    {
      "icon_id": "128976",
      "name": "github",
      "font_class": "github",
      "unicode": "e7ab",
      "unicode_decimal": 59307
    },
    {
      "icon_id": "813700",
      "name": "QQ - 副本",
      "font_class": "qqfuben",
      "unicode": "e629",
      "unicode_decimal": 58921
    },
    {
      "icon_id": "11495057",
      "name": "微信",
      "font_class": "weixin",
      "unicode": "e66c",
      "unicode_decimal": 58988
    },
    {
      "icon_id": "20733463",
      "name": "信",
      "font_class": "changyongtubiao-fuben-72",
      "unicode": "e612",
      "unicode_decimal": 58898
    },
    {
      "icon_id": "436378",
      "name": "首页",
      "font_class": "51",
      "unicode": "e633",
      "unicode_decimal": 58931
    },
    {
      "icon_id": "689262",
      "name": "类目 品类 分类 类别",
      "font_class": "leimupinleifenleileibie",
      "unicode": "e7f9",
      "unicode_decimal": 59385
    },
    {
      "icon_id": "975307",
      "name": "登录",
      "font_class": "denglu",
      "unicode": "e62e",
      "unicode_decimal": 58926
    },
    {
      "icon_id": "6027487",
      "name": "标签",
      "font_class": "biaoqian",
      "unicode": "e601",
      "unicode_decimal": 58881
    },
    {
      "icon_id": "6539416",
      "name": "归档",
      "font_class": "guidang",
      "unicode": "e67e",
      "unicode_decimal": 59006
    },
    {
      "icon_id": "9655525",
      "name": "搜索",
      "font_class": "sousuo",
      "unicode": "e66b",
      "unicode_decimal": 58987
    },
    {
      "icon_id": "14915051",
      "name": "留言板",
      "font_class": "liuyanban-05",
      "unicode": "e630",
      "unicode_decimal": 58928
    }
  ]
}
